nonebug/__init__.py
nonebug/app.py
nonebug/base.py
nonebug/fixture.py
nonebug/mixin/__init__.py
nonebug/mixin/call_api/__init__.py
nonebug/mixin/call_api/fake.py
nonebug/mixin/call_api/model.py
nonebug/mixin/dependent.py
nonebug/mixin/driver.py
nonebug/mixin/process/__init__.py
nonebug/mixin/process/fake.py
nonebug/mixin/process/model.py
nonebug/provider.py
nonebug-0.4.3.dist-info/LICENSE
nonebug-0.4.3.dist-info/METADATA
nonebug-0.4.3.dist-info/WHEEL
nonebug-0.4.3.dist-info/entry_points.txt
nonebug-0.4.3.dist-info/RECORD
