Metadata-Version: 2.1
Name: nonebug
Version: 0.4.3
Summary: nonebot2 test framework
Home-page: https://nonebot.dev/
License: MIT
Keywords: nonebot,pytest,test,bot,onebot,cqhttp
Author: AkiraXie
Author-email: l997460364@outlook.com
Requires-Python: >=3.9,<4.0
Classifier: Framework :: Pytest
Classifier: License :: OSI Approved :: MIT License
Classifier: Programming Language :: Python :: 3
Classifier: Programming Language :: Python :: 3.9
Classifier: Programming Language :: Python :: 3.10
Classifier: Programming Language :: Python :: 3.11
Classifier: Programming Language :: Python :: 3.12
Classifier: Programming Language :: Python :: 3.13
Requires-Dist: asgiref (>=3.4.0,<4.0.0)
Requires-Dist: async-asgi-testclient (>=1.4.8,<2.0.0)
Requires-Dist: nonebot2 (>=2.2.0,<3.0.0)
Requires-Dist: pytest (>=7.0.0,<9.0.0)
Requires-Dist: typing-extensions (>=4.0.0,<5.0.0)
Project-URL: Documentation, https://nonebot.dev/
Project-URL: Repository, https://github.com/nonebot/nonebug
